redhat_opentelemetry_contrib/__init__.py
redhat_opentelemetry_contrib/__version__.py
redhat_opentelemetry_contrib/file_exporters.py
redhat_opentelemetry_contrib/script_instrumentor.py
redhat_opentelemetry_contrib-0.0.0.post6.dev0.dist-info/entry_points.txt
redhat_opentelemetry_contrib-0.0.0.post6.dev0.dist-info/LICENSE
redhat_opentelemetry_contrib-0.0.0.post6.dev0.dist-info/WHEEL
redhat_opentelemetry_contrib-0.0.0.post6.dev0.dist-info/METADATA
redhat_opentelemetry_contrib-0.0.0.post6.dev0.dist-info/RECORD
