Metadata-Version: 2.1
Name: redhat-opentelemetry-contrib
Version: 0.0.0.post6.dev0
Summary: OpenTelementry Python extensions written at Red Hat
License: Apache-2.0
Author: Barak Korren
Author-email: bkorren@redhat.com
Requires-Python: >=3.9.0,<4.0.0
Classifier: License :: OSI Approved :: Apache Software License
Classifier: Programming Language :: Python :: 3
Classifier: Programming Language :: Python :: 3.9
Classifier: Programming Language :: Python :: 3.10
Classifier: Programming Language :: Python :: 3.11
Provides-Extra: instruments
Requires-Dist: opentelemetry-api (>=1.14.0,<2.0.0)
Requires-Dist: opentelemetry-distro (>=0.35b0,<0.36)
Requires-Dist: opentelemetry-sdk (>=1.14.0,<2.0.0)
Requires-Dist: setuptools (>=65.6.3,<66.0.0)
